owncloud/__init__.py
owncloud/bidir_map.py
owncloud/config.py
owncloud/exceptions.py
owncloud/exit_codes.py
owncloud/oc.py
owncloud/occmd.py
owncloud/pkg_info.py
owncloud/progress.py
owncloud/sorted_dict.py
owncloud/utils.py
owncloud/test/__init__.py
owncloud/test/test.py
gtocclient-0.7.1.dist-info/LICENSE.txt
gtocclient-0.7.1.dist-info/METADATA
gtocclient-0.7.1.dist-info/WHEEL
gtocclient-0.7.1.dist-info/entry_points.txt
gtocclient-0.7.1.dist-info/top_level.txt
gtocclient-0.7.1.dist-info/RECORD
