Metadata-Version: 1.1
Name: gtocclient
Version: 0.7.1
Summary: Getui Custom-Developed Python client library for ownCloud
Home-page: UNKNOWN
Author: M1a0
Author-email: support@getui.com
License: LICENSE.txt
Platform: UNKNOWN
Classifier: Programming Language :: Python
Classifier: Programming Language :: Python :: 2
Classifier: Programming Language :: Python :: 3
Classifier: Development Status :: 3 - Alpha
Classifier: Environment :: Web Environment
Classifier: Intended Audience :: Developers
Classifier: Topic :: Internet :: WWW/HTTP
Classifier: Topic :: Software Development :: Libraries :: Python Modules
Classifier: License :: OSI Approved :: MIT License
